bandcalq/__init__.py
bandcalq/bandcalq.py
bandcalq/vqd_custom.py
bandcalq-0.0.1.dist-info/LICENSE
bandcalq-0.0.1.dist-info/METADATA
bandcalq-0.0.1.dist-info/WHEEL
bandcalq-0.0.1.dist-info/top_level.txt
bandcalq-0.0.1.dist-info/RECORD
