Metadata-Version: 2.1
Name: bandcalq
Version: 0.0.1
Summary: Band theory calculations using variational quantum algorithms
Home-page: https://github.com/m-lewand/BandCalQ
Author: Michał Lewandowski
Author-email: michal.lewand99@gmail.com
Classifier: Programming Language :: Python :: 3
Classifier: License :: OSI Approved :: Apache Software License
Classifier: Operating System :: OS Independent
Requires-Python: >=3.9
License-File: LICENSE
Requires-Dist: matplotlib
Requires-Dist: numpy
Requires-Dist: qiskit
Requires-Dist: qiskit-terra
Requires-Dist: tqdm
